{
  "query_id": "491_A",
  "content_id": 2066,
  "explanation": "Correct Calculation:\n\\( 7 \\times \\frac{1}{4} = \\frac{7}{4} \\), which equals \\( 7 \\div 4 \\). The missing value is 4.\n\nStudent's Incorrect Calculation:\nThe student likely set up \\( 7 \\div \\frac{4}{4} \\), treating the divisor as \\(\\frac{4}{4}\\) instead of 4.\n\nSpecific Flaw:\nThe student misapplied fraction division by altering both numerator and denominator of the divisor. They converted the required integer divisor (4) into \\(\\frac{4}{4}\\) by multiplying the denominator (4) by the integer (4), erroneously creating a fraction with equal numerator and denominator.\n\nConnection to Misconception:\nThis stems from the misconception that dividing by a fraction requires multiplying both its numerator and denominator by the integer (here, 4), resulting in \\(\\frac{4}{4}\\) instead of recognizing the divisor as the reciprocal of \\(\\frac{1}{4}\\).\n\nDistinction from Related Errors:\nUnlike errors that confuse multiplication/division operations or misapply reciprocal rules, this specifically alters the divisor's structure by forcing equal numerator and denominator through inappropriate scaling.",
  "timestamp": "2025-04-20T22:00:24.440664",
  "error": null
}