{
  "query_id": "590_A",
  "content_id": 295,
  "explanation": "The correct instrument for constructing circles is a compass, which uses a fixed radius from a central point to create precise circles.  \nThe student selected \"callipers,\" which are tools used to measure distances between two points (like the diameter of an existing object), not to draw circles.  \n\nThe student likely confused the purpose of callipers (measurement of existing circular objects) with the purpose of a compass (construction of new circles). This indicates a misunderstanding of the relationship between circle properties and the tools that utilize them: they associated a measurement device with a circle's diameter (a property) instead of recognizing the tool that applies the radius property to create circles.  \n\nThis directly aligns with the primary misconception of applying the wrong circle property (using a diameter-measurement tool instead of a radius-construction tool), rather than unrelated errors like angle measurement (protractor) or terminology confusion (bisect/diameter).",
  "timestamp": "2025-04-20T22:00:24.440664",
  "error": null
}